slidge_whatsapp/.gopy.sum
slidge_whatsapp/__init__.py
slidge_whatsapp/__main__.py
slidge_whatsapp/avatar.py
slidge_whatsapp/command.py
slidge_whatsapp/config.py
slidge_whatsapp/contact.py
slidge_whatsapp/event.go
slidge_whatsapp/gateway.go
slidge_whatsapp/gateway.py
slidge_whatsapp/generated/__init__.py
slidge_whatsapp/generated/_whatsapp.cpython-313-x86_64-linux-gnu.h
slidge_whatsapp/generated/_whatsapp.cpython-313-x86_64-linux-gnu.so
slidge_whatsapp/generated/build.py
slidge_whatsapp/generated/go.py
slidge_whatsapp/generated/whatsapp.c
slidge_whatsapp/generated/whatsapp.go
slidge_whatsapp/generated/whatsapp.py
slidge_whatsapp/generated/whatsapp_go.h
slidge_whatsapp/go.mod
slidge_whatsapp/go.sum
slidge_whatsapp/group.py
slidge_whatsapp/media/__init__.py
slidge_whatsapp/media/ffmpeg.go
slidge_whatsapp/media/media.go
slidge_whatsapp/media/mupdf.go
slidge_whatsapp/media/stub.go
slidge_whatsapp/session.go
slidge_whatsapp/session.py
slidge_whatsapp/vendor/filippo.io/edwards25519/LICENSE
slidge_whatsapp/vendor/filippo.io/edwards25519/README.md
slidge_whatsapp/vendor/filippo.io/edwards25519/doc.go
slidge_whatsapp/vendor/filippo.io/edwards25519/edwards25519.go
slidge_whatsapp/vendor/filippo.io/edwards25519/extra.go
slidge_whatsapp/vendor/filippo.io/edwards25519/field/fe.go
slidge_whatsapp/vendor/filippo.io/edwards25519/field/fe_amd64.go
slidge_whatsapp/vendor/filippo.io/edwards25519/field/fe_amd64.s
slidge_whatsapp/vendor/filippo.io/edwards25519/field/fe_amd64_noasm.go
slidge_whatsapp/vendor/filippo.io/edwards25519/field/fe_arm64.go
slidge_whatsapp/vendor/filippo.io/edwards25519/field/fe_arm64.s
slidge_whatsapp/vendor/filippo.io/edwards25519/field/fe_arm64_noasm.go
slidge_whatsapp/vendor/filippo.io/edwards25519/field/fe_extra.go
slidge_whatsapp/vendor/filippo.io/edwards25519/field/fe_generic.go
slidge_whatsapp/vendor/filippo.io/edwards25519/scalar.go
slidge_whatsapp/vendor/filippo.io/edwards25519/scalar_fiat.go
slidge_whatsapp/vendor/filippo.io/edwards25519/scalarmult.go
slidge_whatsapp-0.3.10.dist-info/METADATA
slidge_whatsapp-0.3.10.dist-info/WHEEL
slidge_whatsapp-0.3.10.dist-info/entry_points.txt
slidge_whatsapp-0.3.10.dist-info/licenses/LICENSE
slidge_whatsapp-0.3.10.dist-info/RECORD
