Metadata-Version: 2.4
Name: slidge-whatsapp
Version: 0.3.10
Summary: A WhatsApp/XMPP gateway
License-Expression: AGPL-3.0-or-later
License-File: LICENSE
Keywords: xmpp,gateway,bridge,instant messaging,chat,whatsapp
Author: deuill
Author-email: alex@deuill.org
Requires-Python: >= 3.11
Classifier: Topic :: Internet :: XMPP
Requires-Dist: linkpreview (>=0.11.0)
Requires-Dist: slidge (>=0.3.4,<0.4)
Project-URL: Chat room, https://slidge.im/xmpp-web/#/guest?join=slidge@conference.nicoco.fr
Project-URL: Documentation, https://slidge.im/docs/slidge-whatsapp/main
Project-URL: Homepage, https://codeberg.org/slidge/slidge-whatsapp
Project-URL: Issues, https://codeberg.org/slidge/slidge-whatsapp/issues
Project-URL: Repository, https://codeberg.org/slidge/slidge-whatsapp
Project-URL: changelog, https://codeberg.org/slidge/slidge-whatsapp/releases
